congpython/__init__.py
congpython/congfunction_v6.py
tests/__init__.py
tests/test_congfucntion_v6.py
congpython-0.1.dist-info/METADATA
congpython-0.1.dist-info/WHEEL
congpython-0.1.dist-info/top_level.txt
congpython-0.1.dist-info/RECORD
