Metadata-Version: 2.1
Name: congpython
Version: 0.1
Summary: các function cho cong
Author: Cong Le
Author-email: cong.lt91@gmail.com
Classifier: Programming Language :: Python :: 3
Classifier: License :: OSI Approved :: MIT License
Classifier: Operating System :: OS Independent
Requires-Python: >=3.9
